feed2mail/__init__.py
feed2mail/config.py
feed2mail/main.py
feed2mail/render.py
feed2mail/templates/email.html.j2
feed2mail/templates/email.text.j2
feed2mail-0.1.0.dist-info/entry_points.txt
feed2mail-0.1.0.dist-info/LICENSE
feed2mail-0.1.0.dist-info/WHEEL
feed2mail-0.1.0.dist-info/METADATA
feed2mail-0.1.0.dist-info/RECORD
